.git/COMMIT_EDITMSG
.git/config
.git/description
.git/FETCH_HEAD
.git/HEAD
.git/hooks/applypatch-msg.sample
.git/hooks/commit-msg.sample
.git/hooks/fsmonitor-watchman.sample
.git/hooks/post-update.sample
.git/hooks/pre-applypatch.sample
.git/hooks/pre-commit.sample
.git/hooks/pre-merge-commit.sample
.git/hooks/pre-push.sample
.git/hooks/pre-rebase.sample
.git/hooks/pre-receive.sample
.git/hooks/prepare-commit-msg.sample
.git/hooks/push-to-checkout.sample
.git/hooks/sendemail-validate.sample
.git/hooks/update.sample
.git/index
.git/info/exclude
.git/logs/HEAD
.git/logs/refs/heads/distr
.git/logs/refs/heads/github_workflow
.git/logs/refs/heads/ISS14
.git/logs/refs/heads/main
.git/logs/refs/heads/pr10
.git/logs/refs/heads/pr11
.git/logs/refs/heads/pr12
.git/logs/refs/heads/pr13
.git/logs/refs/heads/pr14
.git/logs/refs/heads/pr15
.git/logs/refs/heads/pr2
.git/logs/refs/heads/pr3
.git/logs/refs/heads/pr4
.git/logs/refs/heads/PR5
.git/logs/refs/heads/pr6
.git/logs/refs/heads/pr8
.git/logs/refs/heads/pr9
.git/logs/refs/remotes/origin/distr
.git/logs/refs/remotes/origin/github_workflow
.git/logs/refs/remotes/origin/HEAD
.git/logs/refs/remotes/origin/ISS14
.git/logs/refs/remotes/origin/main
.git/logs/refs/remotes/origin/pr10
.git/logs/refs/remotes/origin/pr12
.git/logs/refs/remotes/origin/pr13
.git/logs/refs/remotes/origin/pr14
.git/logs/refs/remotes/origin/pr15
.git/logs/refs/remotes/origin/pr2
.git/logs/refs/remotes/origin/pr3
.git/logs/refs/remotes/origin/pr4
.git/logs/refs/remotes/origin/PR5
.git/logs/refs/remotes/origin/pr6
.git/logs/refs/remotes/origin/pr8
.git/logs/refs/remotes/origin/pr9
.git/objects/00/e15c53e2190ca590a9fbe6c9b292178568cef8
.git/objects/01/53ccf25d39e1ede671aa7b8f923d9e41890237
.git/objects/01/e234feef599ebafee61c7a0a8685db305d6ccc
.git/objects/03/50c4a3b1b2a53eb2407badf3190c9093aef7f7
.git/objects/03/7585e81567a46b86bdb12cacb8fe7a6b26cc0d
.git/objects/07/10acf175ac4d747e6d387e2813700f078f32be
.git/objects/07/711175e105bcf158fd31e720d28cc69b7e34d5
github_ai_code_review-0.1.0.dist-info/entry_points.txt
github_ai_code_review-0.1.0.dist-info/LICENSE
github_ai_code_review-0.1.0.dist-info/METADATA
github_ai_code_review-0.1.0.dist-info/WHEEL
github_ai_code_review-0.1.0.dist-info/RECORD
